journal_targeter/__init__.py
journal_targeter/admin.py
journal_targeter/colors.py
journal_targeter/demo.py
journal_targeter/doaj.py
journal_targeter/helpers.py
journal_targeter/journals.py
journal_targeter/lookup.py
journal_targeter/mapping.py
journal_targeter/metrics.py
journal_targeter/models.py
journal_targeter/paths.py
journal_targeter/plot.py
journal_targeter/pubmed.py
journal_targeter/ref_loading.py
journal_targeter/reference.py
journal_targeter/scopus.py
journal_targeter/sherpa_romeo.py
journal_targeter/app/__init__.py
journal_targeter/app/admin.py
journal_targeter/app/config.py
journal_targeter/app/models.py
journal_targeter/app/main/__init__.py
journal_targeter/app/main/errors.py
journal_targeter/app/main/forms.py
journal_targeter/app/main/views.py
journal_targeter/app/static/__init__.py
journal_targeter/app/static/custom.css
journal_targeter/app/static/favicon.ico
journal_targeter/app/static/table_colors_full.css
journal_targeter/app/static/table_colors_norefs.css
journal_targeter/app/templates/403.html
journal_targeter/app/templates/404.html
journal_targeter/app/templates/413.html
journal_targeter/app/templates/500.html
journal_targeter/app/templates/_help_ris.html
journal_targeter/app/templates/_info_fit.html
journal_targeter/app/templates/_info_icats.html
journal_targeter/app/templates/_info_jane.html
journal_targeter/app/templates/_info_prospect.html
journal_targeter/app/templates/_info_sources.html
journal_targeter/app/templates/_info_summary.html
journal_targeter/app/templates/_info_table.html
journal_targeter/app/templates/base.html
journal_targeter/app/templates/base_standalone.html
journal_targeter/app/templates/home.html
journal_targeter/app/templates/index.html
journal_targeter/app/templates/macros.html
journal_targeter/app/templates/upload.html
journal_targeter/app/templates/utils.html
journal_targeter/callbacks/__init__.py
journal_targeter/callbacks/cb_metric_weight.js
journal_targeter/callbacks/cb_toggle_all_metrics.js
journal_targeter-1.0.0.dist-info/AUTHORS.md
journal_targeter-1.0.0.dist-info/LICENSE.txt
journal_targeter-1.0.0.dist-info/METADATA
journal_targeter-1.0.0.dist-info/WHEEL
journal_targeter-1.0.0.dist-info/entry_points.txt
journal_targeter-1.0.0.dist-info/top_level.txt
journal_targeter-1.0.0.dist-info/RECORD
