Metadata-Version: 2.1
Name: journal-targeter
Version: 1.0.0
Summary: Journal matching, using title, abstract & references.
Home-page: https://github.com/Townsend-Lab-Yale/journal_targeter
Author: Stephen Gaffney
Author-email: stephen.gaffney@yale.edu
License: GPL-3.0-or-later
Project-URL: Web-app, https://jot.publichealth.yale.edu
Platform: any
Classifier: Development Status :: 4 - Beta
Classifier: Programming Language :: Python
License-File: LICENSE.txt
License-File: AUTHORS.md
Requires-Dist: Flask
Requires-Dist: Bootstrap-Flask
Requires-Dist: Flask-Markdown
Requires-Dist: Flask-Session
Requires-Dist: Flask-WTF
Requires-Dist: PyYAML
Requires-Dist: RISparser
Requires-Dist: beautifulsoup4
Requires-Dist: bokeh (>=2.4.0)
Requires-Dist: html5lib
Requires-Dist: iso4
Requires-Dist: lxml
Requires-Dist: matplotlib
Requires-Dist: numpy
Requires-Dist: pandas
Requires-Dist: python-dotenv
Requires-Dist: requests
Requires-Dist: tabulate
Requires-Dist: xlrd
Requires-Dist: xmltodict
Requires-Dist: zeep
Requires-Dist: appdirs
Requires-Dist: gunicorn
Requires-Dist: gevent
Requires-Dist: rich
Requires-Dist: Flask-SQLAlchemy
Requires-Dist: Flask-Migrate
Requires-Dist: Flask-Moment
Requires-Dist: pyxlsb
Requires-Dist: importlib-metadata ; python_version < "3.8"
Provides-Extra: testing
Requires-Dist: setuptools ; extra == 'testing'
Requires-Dist: pytest ; extra == 'testing'
Requires-Dist: pytest-cov ; extra == 'testing'
Requires-Dist: pytest-check ; extra == 'testing'
Requires-Dist: sphinx ; extra == 'testing'
